wyoming_whisper_cpp/__init__.py
wyoming_whisper_cpp/__main__.py
wyoming_whisper_cpp/handler.py
wyoming_whisper_cpp-2.6.1.dist-info/licenses/LICENSE.md
wyoming_whisper_cpp-2.6.1.dist-info/METADATA
wyoming_whisper_cpp-2.6.1.dist-info/WHEEL
wyoming_whisper_cpp-2.6.1.dist-info/entry_points.txt
wyoming_whisper_cpp-2.6.1.dist-info/top_level.txt
wyoming_whisper_cpp-2.6.1.dist-info/zip-safe
wyoming_whisper_cpp-2.6.1.dist-info/RECORD
