Metadata-Version: 2.4
Name: wyoming-whisper.cpp
Version: 2.6.1
Summary: Wyoming Server for whisper.cpp
Author-email: Laurent Debacker <deback@gmail.com>
License: MIT
Project-URL: Homepage, http://github.com/debackerl/wyoming-whisper.cpp
Keywords: wyoming,whisper,stt
Platform: any
Classifier: Development Status :: 4 - Beta
Classifier: Intended Audience :: End Users/Desktop
Classifier: Topic :: Text Processing :: Linguistic
Classifier: License :: OSI Approved :: MIT License
Classifier: Programming Language :: Python :: 3.7
Classifier: Programming Language :: Python :: 3.8
Classifier: Programming Language :: Python :: 3.9
Classifier: Programming Language :: Python :: 3.10
Classifier: Programming Language :: Python :: 3.11
Classifier: Programming Language :: Python :: 3.12
Requires-Python: >=3.8.1
License-File: LICENSE.md
Requires-Dist: wyoming>=1.5.3
Requires-Dist: pywhispercpp<2,>=1.3.3
Requires-Dist: soxr<1,>=0.3.1
Provides-Extra: dev
Requires-Dist: build==1.3.0; extra == "dev"
Requires-Dist: twine==6.1.0; extra == "dev"
Requires-Dist: black==22.12.0; extra == "dev"
Requires-Dist: flake8==6.0.0; extra == "dev"
Requires-Dist: isort==5.11.3; extra == "dev"
Requires-Dist: mypy==0.991; extra == "dev"
Requires-Dist: pylint==2.15.9; extra == "dev"
Requires-Dist: pytest==7.4.4; extra == "dev"
Requires-Dist: pytest-asyncio==0.23.3; extra == "dev"
Dynamic: license-file
